{
    "BE24-05-02001": {
        "OMR Sheet Number": "2469",
        "QUESTION BOOKLET NUMBER": "A",
        "ROLL NUMBER": "2401209269"
    },
    "BE24-05-02002": {
        "OMR Sheet Number": "2470",
        "QUESTION BOOKLET NUMBER": "B",
        "ROLL NUMBER": "2401209270"
    },
    "BE24-05-02003": {
        "OMR Sheet Number": "2471",
        "QUESTION BOOKLET NUMBER": "A",
        "ROLL NUMBER": "2401209271"
    },
    "BE24-05-02004": {
        "OMR Sheet Number": "2472",
        "QUESTION BOOKLET NUMBER": "B",
        "ROLL NUMBER": "2401209272"
    },
    "BE24-05-02005": {
        "OMR Sheet Number": "2473",
        "QUESTION BOOKLET NUMBER": "A",
        "ROLL NUMBER": "2401209273"
    },
    "BE24-05-02006": {
        "OMR Sheet Number": "2474",
        "QUESTION BOOKLET NUMBER": "B",
        "ROLL NUMBER": "2401209274"
    },
    "BE24-05-02007": {
        "OMR Sheet Number": "2475",
        "QUESTION BOOKLET NUMBER": "A",
        "ROLL NUMBER": "2401209275"
    },
    "BE24-05-02008": {
        "OMR Sheet Number": "2477",
        "QUESTION BOOKLET NUMBER": "A",
        "ROLL NUMBER": "2401209277"
    },
    "BE24-05-02009": {
        "OMR Sheet Number": "2478",
        "QUESTION BOOKLET NUMBER": "B",
        "ROLL NUMBER": "2901209278"
    },
    "BE24-05-02010": {
        "OMR Sheet Number": "2479",
        "QUESTION BOOKLET NUMBER": "4",
        "ROLL NUMBER": "2401209279"
    },
    "BE24-05-02011": {
        "OMR Sheet Number": "2480",
        "QUESTION BOOKLET NUMBER": "None",
        "ROLL NUMBER": "2401209280"
    },
    "BE24-05-02012": {
        "OMR Sheet Number": "2492",
        "QUESTION BOOKLET NUMBER": "B",
        "ROLL NUMBER": "2401209281"
    },
    "BE24-05-02013": {
        "OMR Sheet Number": "2491",
        "QUESTION BOOKLET NUMBER": "A",
        "ROLL NUMBER": "2401209282"
    },
    "BE24-05-02014": {
        "OMR Sheet Number": "2494",
        "QUESTION BOOKLET NUMBER": "B",
        "ROLL NUMBER": "2401209283"
    },
    "BE24-05-02015": {
        "OMR Sheet Number": "2493",
        "QUESTION BOOKLET NUMBER": "A",
        "ROLL NUMBER": "240120928A"
    },
    "BE24-05-02016": {
        "OMR Sheet Number": "2496",
        "QUESTION BOOKLET NUMBER": "B",
        "ROLL NUMBER": "2401209285"
    },
    "BE24-05-02017": {
        "OMR Sheet Number": "2495",
        "QUESTION BOOKLET NUMBER": "A",
        "ROLL NUMBER": "2401209286"
    },
    "BE24-05-02018": {
        "OMR Sheet Number": "2498",
        "QUESTION BOOKLET NUMBER": "B",
        "ROLL NUMBER": "2401209287"
    },
    "BE24-05-02019": {
        "OMR Sheet Number": "2497",
        "QUESTION BOOKLET NUMBER": "A",
        "ROLL NUMBER": "2401209278"
    },
    "BE24-05-02020": {
        "OMR Sheet Number": "24999",
        "QUESTION BOOKLET NUMBER": "A",
        "ROLL NUMBER": "2401209290"
    },
    "BE24-05-02021": {
        "OMR Sheet Number": "2481",
        "QUESTION BOOKLET NUMBER": "A",
        "ROLL NUMBER": "2401209291"
    },
    "BE24-05-02022": {
        "OMR Sheet Number": "2482",
        "QUESTION BOOKLET NUMBER": "B",
        "ROLL NUMBER": "2401209292"
    },
    "BE24-05-02023": {
        "OMR Sheet Number": "2483",
        "QUESTION BOOKLET NUMBER": "A",
        "ROLL NUMBER": "2401209293"
    },
    "BE24-05-02024": {
        "OMR Sheet Number": "2484",
        "QUESTION BOOKLET NUMBER": "B",
        "ROLL NUMBER": "2401209294"
    },
    "BE24-05-02025": {
        "OMR Sheet Number": "2485",
        "QUESTION BOOKLET NUMBER": "A",
        "ROLL NUMBER": "2401209295"
    },
    "BE24-05-02026": {
        "OMR Sheet Number": "2486",
        "QUESTION BOOKLET NUMBER": "B",
        "ROLL NUMBER": "2401209296"
    },
    "BE24-05-02027": {
        "OMR Sheet Number": "2487",
        "QUESTION BOOKLET NUMBER": "A",
        "ROLL NUMBER": "2901209297"
    },
    "BE24-05-02028": {
        "OMR Sheet Number": "24888",
        "QUESTION BOOKLET NUMBER": "B",
        "ROLL NUMBER": "2401209298"
    },
    "BE24-05-02029": {
        "OMR Sheet Number": "2501",
        "QUESTION BOOKLET NUMBER": "A",
        "ROLL NUMBER": "2401209301"
    },
    "BE24-05-02030": {
        "OMR Sheet Number": "2503",
        "QUESTION BOOKLET NUMBER": "A",
        "ROLL NUMBER": "2401209303"
    },
    "BE24-05-02031": {
        "OMR Sheet Number": "2504",
        "QUESTION BOOKLET NUMBER": "B",
        "ROLL NUMBER": "2401209304"
    },
    "BE24-05-02032": {
        "OMR Sheet Number": "2505",
        "QUESTION BOOKLET NUMBER": "A",
        "ROLL NUMBER": "2401209305"
    },
    "BE24-05-02033": {
        "OMR Sheet Number": "2507",
        "QUESTION BOOKLET NUMBER": "A",
        "ROLL NUMBER": "2401209307"
    },
    "BE24-05-02034": {
        "OMR Sheet Number": "2508",
        "QUESTION BOOKLET NUMBER": "None",
        "ROLL NUMBER": "2401209308"
    },
    "BE24-05-02035": {
        "OMR Sheet Number": "2509",
        "QUESTION BOOKLET NUMBER": "a",
        "ROLL NUMBER": "Error: JSONDecodeError",
        "ERROR": "1"
    },
    "BE24-05-02036": {
        "OMR Sheet Number": "2510",
        "QUESTION BOOKLET NUMBER": "B",
        "ROLL NUMBER": "2401209310"
    },
    "BE24-05-02037": {
        "OMR Sheet Number": "2513",
        "QUESTION BOOKLET NUMBER": "A",
        "ROLL NUMBER": "2401209313"
    },
    "BE24-05-02038": {
        "OMR Sheet Number": "2514",
        "QUESTION BOOKLET NUMBER": "B",
        "ROLL NUMBER": "2401209314"
    },
    "BE24-05-02039": {
        "OMR Sheet Number": "2515",
        "QUESTION BOOKLET NUMBER": "A",
        "ROLL NUMBER": "2401209315"
    },
    "BE24-05-02040": {
        "OMR Sheet Number": "2517",
        "QUESTION BOOKLET NUMBER": "A",
        "ROLL NUMBER": "2401209317"
    },
    "BE24-05-02041": {
        "OMR Sheet Number": "Error: JSONDecodeError",
        "QUESTION BOOKLET NUMBER": "B",
        "ROLL NUMBER": "2401209318",
        "ERROR": "1"
    },
    "BE24-05-02042": {
        "OMR Sheet Number": "Error: JSONDecodeError",
        "QUESTION BOOKLET NUMBER": "B",
        "ROLL NUMBER": "2401209320",
        "ERROR": "1"
    },
    "BE24-05-02043": {
        "OMR Sheet Number": "Error: JSONDecodeError",
        "QUESTION BOOKLET NUMBER": "A",
        "ROLL NUMBER": "2401209322",
        "ERROR": "1"
    },
    "BE24-05-02044": {
        "OMR Sheet Number": "2523",
        "QUESTION BOOKLET NUMBER": "A",
        "ROLL NUMBER": "2401209323"
    },
    "BE24-05-02045": {
        "OMR Sheet Number": "2524",
        "QUESTION BOOKLET NUMBER": "B",
        "ROLL NUMBER": "2401209324"
    },
    "BE24-05-02046": {
        "OMR Sheet Number": "2526",
        "QUESTION BOOKLET NUMBER": "B.",
        "ROLL NUMBER": "2401209326"
    },
    "BE24-05-02047": {
        "OMR Sheet Number": "2527",
        "QUESTION BOOKLET NUMBER": "A",
        "ROLL NUMBER": "2401209327"
    },
    "BE24-05-02048": {
        "OMR Sheet Number": "2528",
        "QUESTION BOOKLET NUMBER": "B",
        "ROLL NUMBER": "2401209328"
    },
    "BE24-05-02049": {
        "OMR Sheet Number": "2530",
        "QUESTION BOOKLET NUMBER": "B",
        "ROLL NUMBER": "2401209330"
    },
    "BE24-05-02050": {
        "OMR Sheet Number": "2531",
        "QUESTION BOOKLET NUMBER": "A",
        "ROLL NUMBER": "2401209331"
    }
}